{
  "company": {
    "name": "Nascent Info Technologies Pvt. Ltd.",
    "short_name": "Nascent",
    "cin": "U72200GJ2006PTC048723",
    "pan": "AACCN3670J",
    "gstin": "24AACCN3670J1ZG",
    "msme_udyam": "UDYAM-GJ-01-0007420",
    "msme_type": "Service Provider",
    "incorporated": "23 June 2006",
    "years_in_operation": 19,
    "type": "Private Limited",
    "address": "A-805, Shapath IV, SG Highway, Prahlad Nagar, Ahmedabad \u2013 380015, Gujarat",
    "city": "Ahmedabad",
    "state": "Gujarat",
    "pin": "380015",
    "phone": "+91-79-40200400",
    "email": "nascent.tender@nascentinfo.com",
    "website": "www.nascentinfo.com",
    "bank": "State Bank of India, SG Highway Branch, Ahmedabad",
    "bank_account": "[to be filled]",
    "bank_ifsc": "[to be filled]",
    "total_employees": "67",
    "udyam": "UDYAM-GJ-01-0007420",
    "msme": true,
    "legal_status": "Private Limited Company",
    "year_of_incorporation": 2006,
    "authorised_signatory": "Hitesh Patel \u2014 Chief Administrative Officer",
    "md": "Maulik Bhagat",
    "din_md": "",
    "poa_validity": "01/04/2025 \u2014 31/03/2026 (EXPIRED)",
    "poa_alert": "\u26a0 POA of Hitesh Patel EXPIRED 31-Mar-2026 \u2014 MUST RENEW before any bid submission",
    "tender_email": "nascent.tender@nascentinfo.com",
    "gem_seller_id": "",
    "alternate_address": ""
  },
  "authorised_signatory": {
    "name": "Hitesh Patel",
    "designation": "Chief Administrative Officer",
    "din": "[to be filled]"
  },
  "bid_executive": {
    "name": "Parthav Thakkar",
    "designation": "Bid Executive",
    "email": "parthav@nascentinfo.com",
    "phone": "[to be filled]"
  },
  "employees": {
    "total": 67,
    "gis_specialists": 11,
    "it_developers": 21,
    "qa_pm_ba_support": 35,
    "epf_registered": true,
    "total_confirmed": 67,
    "it_dev_staff": 21,
    "gis_staff": 11
  },
  "certifications": {
    "cmmi": {
      "level": 3,
      "version": "V2.0 (DEV)",
      "benchmark_id": "68617",
      "issuer": "CUNIX Infotech Pvt. Ltd.",
      "valid_from": "14-Dec-2023",
      "valid_to": "19-Dec-2026",
      "status": "ACTIVE"
    },
    "iso_9001": {
      "standard": "ISO 9001:2015",
      "cert_no": "25EQPE64",
      "issuer": "Assurance Quality Certification LLC",
      "valid_from": "09-Sep-2025",
      "valid_to": "08-Sep-2028",
      "status": "ACTIVE"
    },
    "iso_27001": {
      "standard": "ISO/IEC 27001:2022",
      "cert_no": "25EQPG58",
      "issuer": "Assurance Quality Certification LLC",
      "valid_from": "09-Sep-2025",
      "valid_to": "08-Sep-2028",
      "status": "ACTIVE"
    },
    "iso_20000": {
      "standard": "ISO/IEC 20000-1:2018",
      "cert_no": "25ZQZQ030409IT",
      "issuer": "International Quality Certification Services UK Ltd",
      "valid_from": "09-Sep-2025",
      "valid_to": "08-Sep-2028",
      "status": "ACTIVE"
    },
    "cert_in": false,
    "stqc": false,
    "ogc": {
      "standard": "OGC Compliance - CityLayers 2.0",
      "pid": "1600",
      "status": "ACTIVE"
    }
  },
  "domains": [
    "GIS Application Development",
    "Mobile Application Development (Android & iOS)",
    "Smart City Solutions",
    "eGovernance Portals",
    "ERP / Enterprise Systems",
    "Field Survey & Data Collection",
    "Web Application Development",
    "Database Design & Management",
    "Cloud & Deployment Services"
  ],
  "key_technologies": [
    "QGIS",
    "GeoServer",
    "PostGIS",
    "CityLayers 2.0",
    "OpenLayers",
    "MapLibre",
    "Android (Java/Kotlin)",
    "iOS (Swift)",
    "Flutter",
    "Java Spring Boot",
    "Python FastAPI",
    "React.js",
    "Angular",
    "PostgreSQL",
    "MySQL",
    "MongoDB",
    "Redis",
    "Docker",
    "Jenkins",
    "Git",
    "AWS",
    "Azure",
    "OAuth 2.0",
    "JWT",
    "SSL/TLS"
  ],
  "projects": [
    {
      "id": "P001",
      "name": "AMC GIS \u2013 Ahmedabad Municipal Corporation",
      "client": "Ahmedabad Municipal Corporation",
      "client_type": "ULB / Municipal Corporation",
      "state": "Gujarat",
      "value_lakhs": 1055,
      "value_display": "Rs. 10.55 Cr",
      "status": "Ongoing AMC",
      "year_started": 2018,
      "year_completed": null,
      "domains": [
        "gis",
        "mobile",
        "ulb",
        "municipal",
        "smart city",
        "ahmedabad"
      ],
      "scope": "Web GIS, property mapping, road network, utilities, ward boundary management, field staff mobile app, GPS tracking, ongoing AMC support",
      "technologies": [
        "GeoServer",
        "PostGIS",
        "QGIS",
        "Android",
        "React.js",
        "Java Spring Boot"
      ],
      "completion_certificate": true,
      "contact_person": "[to be filled]",
      "wo_no": "AMC/GIS/2018/001",
      "wo_date": "15-Jun-2018",
      "wo_value_lakhs": 1055,
      "loi_received": "Yes",
      "loi_date": "01-Jun-2018",
      "completion_cert": "Ongoing - AMC",
      "outcome": "Ongoing",
      "client_contact": "",
      "similar_categories": [
        "GIS",
        "ULB",
        "Web GIS",
        "Property Mapping",
        "Mobile App"
      ]
    },
    {
      "id": "P002",
      "name": "JuMC GIS \u2013 Junagadh Municipal Corporation",
      "client": "Junagadh Municipal Corporation",
      "client_type": "ULB / Municipal Corporation",
      "state": "Gujarat",
      "value_lakhs": 978,
      "value_display": "Rs. 9.78 Cr",
      "status": "Ongoing",
      "year_started": 2020,
      "year_completed": null,
      "domains": [
        "gis",
        "municipal",
        "ulb",
        "survey",
        "junagadh"
      ],
      "scope": "Web GIS, mobile survey application, GIS layer management, property mapping, ongoing AMC",
      "technologies": [
        "GeoServer",
        "PostGIS",
        "Android",
        "React.js"
      ],
      "completion_certificate": false,
      "wo_no": "JuMC/GIS/2020/007",
      "wo_date": "20-Mar-2020",
      "wo_value_lakhs": 978,
      "loi_received": "Yes",
      "loi_date": "10-Mar-2020",
      "completion_cert": "No - Ongoing",
      "outcome": "Ongoing",
      "client_contact": "",
      "similar_categories": [
        "GIS",
        "Survey",
        "ULB",
        "Web GIS"
      ]
    },
    {
      "id": "P003",
      "name": "BMC GIS Mobile App \u2013 Bhavnagar Municipal Corporation",
      "client": "Bhavnagar Municipal Corporation",
      "client_type": "ULB / Municipal Corporation",
      "state": "Gujarat",
      "value_lakhs": 420,
      "value_display": "Rs. 4.2 Cr",
      "status": "Completed",
      "year_started": 2021,
      "year_completed": 2022,
      "domains": [
        "gis",
        "mobile",
        "android",
        "ios",
        "app",
        "ulb",
        "municipal",
        "field",
        "geo-tagging",
        "offline"
      ],
      "scope": "Android + iOS GIS Mobile Application, field survey, geo-tagging, offline mode, GeoServer WMS/WFS integration, role-based access, sync engine",
      "technologies": [
        "Android",
        "iOS",
        "GeoServer",
        "PostGIS",
        "MapLibre",
        "SQLite",
        "Spring Boot"
      ],
      "completion_certificate": true,
      "is_identical_to": [
        "GIS Mobile App",
        "Mobile GIS",
        "Field GIS App"
      ],
      "wo_no": "BMC/IT/2021/015",
      "wo_date": "15-Apr-2021",
      "wo_value_lakhs": 420,
      "loi_received": "Yes",
      "loi_date": "01-Apr-2021",
      "completion_cert": "Yes - 20-Mar-2022",
      "outcome": "Completed",
      "client_contact": "",
      "similar_categories": [
        "Mobile App",
        "GIS",
        "Android",
        "iOS",
        "ULB",
        "Offline GIS"
      ]
    },
    {
      "id": "P004",
      "name": "VMC GIS + ERP \u2013 Vadodara Municipal Corporation",
      "client": "Vadodara Municipal Corporation",
      "client_type": "ULB / Municipal Corporation",
      "state": "Gujarat",
      "value_lakhs": 2050,
      "value_display": "Rs. 20.5 Cr",
      "status": "Completed",
      "year_started": 2017,
      "year_completed": 2020,
      "domains": [
        "gis",
        "erp",
        "municipal",
        "ulb",
        "vadodara",
        "large scale"
      ],
      "scope": "Web GIS, property management, ERP modules (HR, Finance, Inventory), large-scale ULB deployment",
      "technologies": [
        "GeoServer",
        "PostGIS",
        "Java",
        "React.js",
        "Oracle"
      ],
      "completion_certificate": true,
      "wo_no": "VMC/GIS/2017/003",
      "wo_date": "10-Aug-2017",
      "wo_value_lakhs": 2050,
      "loi_received": "Yes",
      "loi_date": "25-Jul-2017",
      "completion_cert": "Yes - 15-Jan-2021",
      "outcome": "Completed",
      "client_contact": "",
      "similar_categories": [
        "GIS",
        "ERP",
        "ULB",
        "Web GIS",
        "Property"
      ]
    },
    {
      "id": "P005",
      "name": "KVIC Mobile GIS \u2013 Khadi Village Industries Commission",
      "client": "Khadi Village Industries Commission (KVIC)",
      "client_type": "Central Government PSU",
      "state": "PAN India",
      "value_lakhs": 515,
      "value_display": "Rs. 5.15 Cr",
      "status": "Completed",
      "year_started": 2019,
      "year_completed": 2021,
      "domains": [
        "gis",
        "mobile",
        "android",
        "field",
        "geo-tagging",
        "offline",
        "central",
        "psu",
        "survey"
      ],
      "scope": "PAN India mobile GIS application, geo-tagging, offline data collection, sync with central server, field staff GPS tracking",
      "technologies": [
        "Android",
        "PostGIS",
        "Python FastAPI",
        "SQLite",
        "Google Maps API"
      ],
      "completion_certificate": true,
      "wo_no": "KVIC/IT/2019/022",
      "wo_date": "05-Sep-2019",
      "wo_value_lakhs": 515,
      "loi_received": "Yes",
      "loi_date": "20-Aug-2019",
      "completion_cert": "Yes - 30-Jun-2021",
      "outcome": "Completed",
      "client_contact": "",
      "similar_categories": [
        "Mobile GIS",
        "Survey",
        "Central Govt",
        "Geo-tagging",
        "PAN India",
        "Offline"
      ]
    },
    {
      "id": "P006",
      "name": "PCSCL Smart City \u2013 Pimpri-Chinchwad Smart City",
      "client": "Pimpri Chinchwad Smart City Corp Ltd (PCSCL)",
      "client_type": "Smart City SPV",
      "state": "Maharashtra",
      "value_lakhs": 6119,
      "value_display": "Rs. 61.19 Cr",
      "status": "Ongoing",
      "year_started": 2019,
      "year_completed": null,
      "domains": [
        "smart city",
        "gis",
        "erp",
        "scada",
        "iot",
        "municipal",
        "large scale"
      ],
      "scope": "Integrated Smart City platform \u2014 GIS, ERP, SCADA, IoT dashboards, citizen portal, command & control centre",
      "technologies": [
        "GeoServer",
        "PostGIS",
        "Java Spring Boot",
        "React.js",
        "Apache Kafka",
        "Docker"
      ],
      "completion_certificate": false,
      "wo_no": "PCSCL/GIS/2019/001",
      "wo_date": "01-Feb-2019",
      "wo_value_lakhs": 6119,
      "loi_received": "Yes",
      "loi_date": "15-Jan-2019",
      "completion_cert": "No - Ongoing",
      "outcome": "Ongoing",
      "client_contact": "",
      "similar_categories": [
        "Smart City",
        "GIS",
        "ERP",
        "IoT",
        "ULB",
        "Large Scale"
      ]
    },
    {
      "id": "P007",
      "name": "AMC Heritage App (AHA) \u2013 Ahmedabad Smart City",
      "client": "Ahmedabad Smart City Development Ltd",
      "client_type": "Smart City SPV",
      "state": "Gujarat",
      "value_lakhs": 380,
      "value_display": "Rs. 3.8 Cr",
      "status": "Completed",
      "year_started": 2021,
      "year_completed": 2022,
      "domains": [
        "mobile",
        "android",
        "ios",
        "ar",
        "augmented reality",
        "heritage",
        "smart city",
        "ahmedabad",
        "tourism"
      ],
      "scope": "Heritage mobile application with Augmented Reality (AR), QR code integration, GPS-based location experiences, multilingual support",
      "technologies": [
        "Android",
        "iOS",
        "AR Kit / AR Core",
        "Unity 3D",
        "Node.js"
      ],
      "completion_certificate": true,
      "wo_no": "ASCL/APP/2021/008",
      "wo_date": "10-Jun-2021",
      "wo_value_lakhs": 380,
      "loi_received": "Yes",
      "loi_date": "01-Jun-2021",
      "completion_cert": "Yes - 31-Mar-2022",
      "outcome": "Completed",
      "client_contact": "",
      "similar_categories": [
        "Mobile App",
        "AR",
        "Tourism",
        "Smart City"
      ]
    },
    {
      "id": "P008",
      "name": "NSO FOD Survey \u2013 National Statistics Office",
      "client": "National Statistics Office (NSO) / MoSPI",
      "client_type": "Central Government Ministry",
      "state": "PAN India",
      "value_lakhs": 840,
      "value_display": "Rs. 8.4 Cr",
      "status": "Completed",
      "year_started": 2020,
      "year_completed": 2022,
      "domains": [
        "survey",
        "mobile",
        "android",
        "field",
        "gis",
        "central",
        "government",
        "data collection",
        "enumeration"
      ],
      "scope": "Mobile field data collection app for NSO field investigators, household survey forms, geo-tagging, supervisor dashboard, real-time sync",
      "technologies": [
        "Android",
        "Python FastAPI",
        "PostgreSQL",
        "GeoServer",
        "React.js"
      ],
      "completion_certificate": true,
      "wo_no": "NSO/IT/2020/045",
      "wo_date": "20-Nov-2020",
      "wo_value_lakhs": 840,
      "loi_received": "Yes",
      "loi_date": "05-Nov-2020",
      "completion_cert": "Yes - 28-Feb-2022",
      "outcome": "Completed",
      "client_contact": "",
      "similar_categories": [
        "Survey",
        "Mobile",
        "Central Govt",
        "Data Collection",
        "PAN India"
      ]
    },
    {
      "id": "P009",
      "name": "NP Lalganj GIS \u2013 Nagar Panchayat Lalganj",
      "client": "Nagar Panchayat Lalganj",
      "client_type": "ULB / Nagar Panchayat",
      "state": "Uttar Pradesh",
      "value_lakhs": 120,
      "value_display": "Rs. 1.2 Cr",
      "status": "Completed",
      "year_started": 2023,
      "year_completed": 2024,
      "domains": [
        "gis",
        "municipal",
        "ulb",
        "property",
        "survey"
      ],
      "scope": "GIS-based property survey and mapping for Nagar Panchayat, ward boundary digitisation, property tax module integration",
      "technologies": [
        "QGIS",
        "GeoServer",
        "PostGIS",
        "Python"
      ],
      "completion_certificate": true,
      "wo_no": "NPL/GIS/2023/002",
      "wo_date": "15-Apr-2023",
      "wo_value_lakhs": 120,
      "loi_received": "Yes",
      "loi_date": "01-Apr-2023",
      "completion_cert": "Yes - 30-Jun-2024",
      "outcome": "Completed",
      "client_contact": "",
      "similar_categories": [
        "GIS",
        "ULB",
        "Property",
        "Survey"
      ]
    },
    {
      "id": "P010",
      "name": "SMC GIS Mobile App \u2013 Surat Municipal Corporation",
      "client": "Surat Municipal Corporation",
      "client_type": "ULB / Municipal Corporation",
      "state": "Gujarat",
      "value_lakhs": null,
      "value_display": "Tendering",
      "status": "Bidding",
      "year_started": null,
      "year_completed": null,
      "domains": [
        "gis",
        "mobile",
        "android",
        "ios",
        "ulb",
        "municipal",
        "surat",
        "field",
        "geo-tagging"
      ],
      "scope": "Design, Development, Implementation and AMC of GIS Mobile Application using existing GIS infrastructure (2nd Attempt)",
      "tender_no": "DC/GIS CELL/04/2025-26",
      "tender_id": "283807",
      "portal": "smctender.nprocure.com",
      "wo_no": "SMC/DC/GIS CELL/04/2025-26",
      "wo_date": "",
      "wo_value_lakhs": 0,
      "loi_received": "Bidding",
      "loi_date": "",
      "completion_cert": "Pending",
      "outcome": "Bidding",
      "client_contact": "",
      "similar_categories": [
        "GIS",
        "Mobile App",
        "ULB",
        "Android",
        "iOS"
      ]
    }
  ],
  "standard_documents": {
    "cover_letter": true,
    "non_blacklisting_declaration": true,
    "financial_standing_undertaking": true,
    "make_in_india_declaration": true,
    "employee_strength_declaration": true,
    "msme_emd_exemption_letter": true,
    "ca_turnover_certificate_format": true
  },
  "emd_exemption": {
    "eligible": true,
    "basis": "MSME Service Provider \u2014 Public Procurement Policy for MSMEs Order 2012 (amended 2018)",
    "reference": "DoE OM F.No.6/18/2019-PPD dated 16.11.2020"
  },
  "metadata": {
    "last_updated": "2026-03-19",
    "version": "2.0",
    "updated_by": "Bid/No-Bid System"
  },
  "bid_rules": {
    "min_project_value_cr": 0.5,
    "max_project_value_cr": 150,
    "preferred_sectors": [
      "gis",
      "geospatial",
      "geo-spatial",
      "geographic information",
      "gis solution",
      "gis portal",
      "gis application",
      "gis software",
      "web gis",
      "mobile gis",
      "qgis",
      "arcgis",
      "geoserver",
      "smart city",
      "smart cities",
      "city surveillance",
      "urban",
      "municipal",
      "municipality",
      "municipal corporation",
      "nagar palika",
      "nagar nigam",
      "nagar panchayat",
      "mobile application",
      "mobile app",
      "android application",
      "ios application",
      "mobile survey",
      "field survey",
      "egovernance",
      "e-governance",
      "citizen portal",
      "citizen services",
      "government portal",
      "web portal",
      "online portal",
      "erp",
      "enterprise resource planning",
      "asset management",
      "property management",
      "property tax",
      "water supply",
      "sewerage",
      "drainage",
      "solid waste",
      "grievance",
      "complaint management",
      "citizen grievance",
      "land records",
      "land management",
      "survey settlement",
      "geo tagging",
      "geotagging",
      "geo-tagging",
      "it services",
      "software development",
      "application development",
      "custom software",
      "web application",
      "web development",
      "data analytics",
      "dashboard",
      "mis report",
      "annual maintenance",
      "amc",
      "facility management",
      "digitization",
      "digitisation",
      "data entry",
      "data conversion",
      "mapping",
      "maps",
      "remote sensing",
      "satellite"
    ],
    "do_not_bid": [
      "road construction",
      "road repair",
      "road maintenance",
      "construction of",
      "building construction",
      "civil work",
      "bridge",
      "flyover",
      "culvert",
      "dam",
      "canal",
      "pavement",
      "footpath",
      "street light installation",
      "electrical installation",
      "electrical work",
      "supply of material",
      "supply of goods",
      "purchase of vehicle",
      "procurement of vehicle",
      "firefighting",
      "fire equipment",
      "plumbing",
      "sanitation work",
      "horticulture",
      "garden",
      "plantation",
      "printing of",
      "stationery",
      "offset printing",
      "security guard",
      "security service",
      "housekeeping",
      "manpower supply",
      "labour supply",
      "workforce",
      "medicine",
      "pharmaceutical",
      "medical equipment",
      "hospital equipment",
      "ambulance",
      "catering",
      "food supply",
      "canteen",
      "supply of computer",
      "purchase of computer",
      "laptop procurement",
      "supply of server",
      "networking equipment supply",
      "statutory audit",
      "tax audit",
      "legal services",
      "insurance policy",
      "life insurance",
      "sewerage network",
      "sewerage pipeline",
      "sewerage laying",
      "procurement of security",
      "hiring of security",
      "deployment of security",
      "supply and installation of road",
      "road laying",
      "road widening",
      "construction and maintenance of road"
    ],
    "do_not_bid_remarks": {
      "road construction": "Civil construction \u2014 not Nascent domain",
      "civil work": "Civil work \u2014 not Nascent domain",
      "construction of": "Civil construction \u2014 not Nascent domain",
      "supply of material": "Material supply only \u2014 not IT/software",
      "security guard": "Security manpower \u2014 not Nascent domain",
      "housekeeping": "Facility management manpower \u2014 not IT",
      "catering": "Catering services \u2014 not Nascent domain",
      "printing of": "Printing services \u2014 not Nascent domain",
      "medicine": "Pharmaceutical \u2014 not Nascent domain",
      "insurance": "Insurance \u2014 not Nascent domain",
      "electrical work": "Electrical installation \u2014 not IT domain",
      "sewerage network": "Civil pipeline work \u2014 not IT/software",
      "sewerage pipeline": "Civil pipeline work \u2014 not IT/software",
      "procurement of security": "Security manpower supply \u2014 not Nascent domain",
      "hiring of security": "Security manpower \u2014 not Nascent domain"
    },
    "conditional": [
      "cert-in",
      "cert in empanelled",
      "stqc",
      "meity empanelled",
      "sap partner",
      "oracle partner",
      "sap certified",
      "local office",
      "office in state",
      "registered in state",
      "state registration",
      "office in gujarat",
      "branch office",
      "minimum 100 employees",
      "minimum 200 employees",
      "atleast 100",
      "at least 100 staff",
      "200 employees",
      "consortium",
      "joint venture",
      "jv partner",
      "dot net",
      ".net framework",
      "asp.net",
      "microsoft stack",
      "ms sql",
      "microsoft sql",
      "sql server",
      "sap implementation",
      "oracle implementation",
      "average turnover of rs. 50",
      "average turnover of rs.50",
      "turnover of 50 cr",
      "turnover of 100 cr",
      "data center",
      "own data center",
      "tier iii"
    ],
    "urgent_keywords": [
      "corrigendum",
      "extension",
      "pre-bid"
    ]
  },
  "finance": {
    "turnover_by_year": {
      "2022-23": 16.36,
      "2023-24": 16.36,
      "2024-25": 18.83,
      "2019-20": 17.42,
      "2020-21": 9.17,
      "2021-22": 20.42
    },
    "avg_turnover_last_3_fy": 17.18,
    "avg_turnover_cr": 17.18,
    "net_worth_cr": 26.09,
    "solvency_amount_cr": 2.61,
    "ca_name": "Anuj J. Sharedalal",
    "avg_turnover_last_2_fy": 17.6,
    "avg_turnover_last_5_fy": 16.23
  },
  "technology": {
    "core_stack": [
      "Java/Spring Boot",
      "Python/FastAPI",
      "React.js",
      "Angular",
      "Flutter",
      "Android"
    ],
    "gis_stack": [
      "QGIS",
      "ArcGIS",
      "GeoServer",
      "PostGIS",
      "CityLayers 2.0",
      "OpenLayers",
      "MapLibre"
    ],
    "database": [
      "PostgreSQL",
      "MySQL",
      "MongoDB",
      "Redis"
    ],
    "cloud": [
      "AWS",
      "Azure",
      "Docker",
      "Jenkins"
    ],
    "not_available": [
      "Microsoft .NET",
      "MS SQL Server",
      "SAP",
      "Oracle ERP",
      "CERT-In empanelment",
      "STQC"
    ]
  }
}